app/__init__.py
app/main.py
appwithpipeline-0.1.3.dist-info/METADATA
appwithpipeline-0.1.3.dist-info/WHEEL
appwithpipeline-0.1.3.dist-info/top_level.txt
appwithpipeline-0.1.3.dist-info/RECORD
