Metadata-Version: 2.4
Name: appwithpipeline
Version: 0.1.3
Summary: Sample app for Jenkins CI/CD packaging
Author-email: Nikita <nikzakharenkov@gmail.com>
Requires-Python: >=3.9
